Metadata-Version: 2.4
Name: pentestai-cli
Version: 1.1.0
Summary: PentestAI - AI-assisted pentest CLI workflow (recon -> analysis -> scan -> validate -> report)
Author: Dinhvaren
License: MIT
Requires-Python: >=3.12
License-File: LICENSE
Requires-Dist: typer>=0.12
Requires-Dist: rich>=13
Requires-Dist: pydantic==2.10.6
Requires-Dist: pyyaml==6.0.2
Requires-Dist: python-dotenv==1.0.1
Requires-Dist: httpx==0.27.2
Requires-Dist: click==8.1.7
Dynamic: license-file
